git_repo/__init__.py
git_repo/cli.py
git_repo/config.py
git_repo/git_repository.py
git_repo/parse_args.py
git_repo/utils.py
git_repo/gitignore/default.gitignore
git_repo_cli-1.3.5.dist-info/LICENSE.md
git_repo_cli-1.3.5.dist-info/METADATA
git_repo_cli-1.3.5.dist-info/WHEEL
git_repo_cli-1.3.5.dist-info/entry_points.txt
git_repo_cli-1.3.5.dist-info/top_level.txt
git_repo_cli-1.3.5.dist-info/RECORD
