Metadata-Version: 2.1
Name: git-repo-cli
Version: 1.3.5
Summary: Utils to easily create/delete/rename repository.
Home-page: https://github.com/VoIlAlex/git-repo-cli
Author: Ilya Vouk
Author-email: ilya.vouk@gmail.com
License: MIT
Download-URL: https://github.com/VoIlAlex/git-repo/archive/v1.2.0.tar.gz
Keywords: VCS,Git,GitHub,utility,cli
Platform: UNKNOWN
Classifier: Development Status :: 4 - Beta
Classifier: Intended Audience :: Developers
Classifier: Topic :: Software Development :: Version Control :: Git
Classifier: Environment :: Console
Classifier: License :: OSI Approved :: MIT License
Classifier: Programming Language :: Python :: 3
Classifier: Programming Language :: Python :: 3.5
Classifier: Programming Language :: Python :: 3.6
Classifier: Programming Language :: Python :: 3.7
License-File: LICENSE.md
Requires-Dist: PyGithub
Requires-Dist: GitPython
Requires-Dist: colored
